upkie_locomotion/__init__.py
upkie_locomotion/envs/BUILD
upkie_locomotion/envs/__init__.py
upkie_locomotion/envs/standing_reward.py
upkie_locomotion/envs/upkie_base_env.py
upkie_locomotion/envs/upkie_servos_env.py
upkie_locomotion/envs/upkie_wheels_env.py
upkie_locomotion/envs/tests/BUILD
upkie_locomotion/envs/tests/upkie_base_env_test.py
upkie_locomotion/envs/tests/upkie_wheels_env_test.py
upkie_locomotion/observers/base_pitch/BUILD
upkie_locomotion/observers/base_pitch/__init__.py
upkie_locomotion/observers/base_pitch/base_pitch.py
upkie_locomotion/observers/base_pitch/tests/BUILD
upkie_locomotion/observers/base_pitch/tests/base_pitch_test.py
upkie_locomotion/utils/BUILD
upkie_locomotion/utils/clamp.py
upkie_locomotion/utils/filters.py
upkie_locomotion/utils/logging.py
upkie_locomotion/utils/pinocchio.py
upkie_locomotion/utils/realtime.py
upkie_locomotion/utils/spdlog.py
upkie_locomotion/utils/tests/BUILD
upkie_locomotion/utils/tests/clamp_test.py
upkie_locomotion/utils/tests/pinocchio_test.py
upkie_locomotion-0.4.0.dist-info/WHEEL
upkie_locomotion-0.4.0.dist-info/METADATA
upkie_locomotion-0.4.0.dist-info/RECORD
