Metadata-Version: 2.1
Name: upkie_locomotion
Version: 0.4.0
Summary: Real-time motion control for Python.
Keywords: motion control,real time,robotics
Author-email: Stéphane Caron <stephane.caron@normalesup.org>
Maintainer-email: Stéphane Caron <stephane.caron@normalesup.org>
Requires-Python: >=3.7
Classifier: Development Status :: 4 - Beta
Classifier: Framework :: Robot Framework :: Library
Classifier: Intended Audience :: Developers
Classifier: Intended Audience :: Science/Research
Classifier: License :: OSI Approved :: Apache Software License
Classifier: Operating System :: OS Independent
Classifier: Programming Language :: Python :: 3
Classifier: Programming Language :: Python :: 3.10
Classifier: Programming Language :: Python :: 3.7
Classifier: Programming Language :: Python :: 3.8
Classifier: Programming Language :: Python :: 3.9
Classifier: Topic :: Scientific/Engineering
Requires-Dist: gym >=0.21.0
Requires-Dist: loop-rate-limiters >=0.2.0
Requires-Dist: numpy >=1.22.0
Requires-Dist: qpsolvers >=1.9.1
Requires-Dist: upkie_description >=1.2.0
Requires-Dist: vulp >=1.1.1
Project-URL: Changelog, https://github.com/tasts-robots/upkie_locomotion/blob/main/CHANGELOG.md
Project-URL: Documentation, https://tasts-robots.org/doc/upkie_locomotion/
Project-URL: Source, https://github.com/tasts-robots/upkie_locomotion
Project-URL: Tracker, https://github.com/tasts-robots/upkie_locomotion/issues
